./.gitignore
./.readthedocs.yaml
./PKG-INFO
./README.md
./mkdocs.yml
./pyproject.toml
./pyrightconfig.json
./docs/index.md
./penguin/alaska.py
./penguin/iceberg.py
./penguin/igloo.py
./penguin/main.py
./penguin/tundra.py
py_penguin-0.1.0.dist-info/METADATA
py_penguin-0.1.0.dist-info/WHEEL
py_penguin-0.1.0.dist-info/RECORD
