Metadata-Version: 2.1
Name: py-penguin
Version: 0.1.0
Summary: A mini penguin framework
Project-URL: Homepage, https://github.com/MuriloCarlos1567/penguin
Project-URL: Issues, https://github.com/MuriloCarlos1567/penguin/issues
Author-email: Murilo Carlos <efgs96@gmail.com>
Classifier: License :: OSI Approved :: MIT License
Classifier: Operating System :: OS Independent
Classifier: Programming Language :: Python :: 3
Requires-Python: >=3.9
Requires-Dist: psycopg2
Requires-Dist: pymysql
